[
    {
      "href": "/external/https%3A%2F%2Fwww.nintendo.com%2Fstore%2F",
      "companyName": "Nintendo",
      "tag": "GumGum Stories"
    },
    {
      "href": "/external/https%3A%2F%2Fen.wikipedia.org%2Fwiki%2FAldi",
      "companyName": "Aldi",
      "tag": "In Screen Expandable"
    },
    {
      "href": "/external/https%3A%2F%2Fen.wikipedia.org%2Fwiki%2FPopeyes",
      "companyName": "Popeyes",
      "tag": "In-Article Video"
    },
    {
      "href": "/external/https%3A%2F%2Fen.wikipedia.org%2Fwiki%2FHonda",
      "companyName": "Honda",
      "tag": "In-Article Video"
    },
    {
      "href": "/external/https%3A%2F%2Fen.wikipedia.org%2Fwiki%2FChase",
      "companyName": "Chase",
      "tag": "In Screen Expandable"
    },
    {
      "href": "/external/https%3A%2F%2Fen.wikipedia.org%2Fwiki%2FHobo",
      "companyName": "HOBO",
      "tag": "In Screen Expandable"
    },
    {
      "href": "/external/https%3A%2F%2Fen.wikipedia.org%2Fwiki%2FFord",
      "companyName": "Ford",
      "tag": "In Screen Expandable"
    },
    {
      "href": "/external/https%3A%2F%2Fen.wikipedia.org%2Fwiki%2FStarbucks",
      "companyName": "Starbucks",
      "tag": "In Screen Expandable"
    }
  ]
  